{
  "chattings": [
    {
      "chatRoomId": 0,
      "userList": [0, 1],
      "chatList": [
        {
          "id": 0,
          "senderId": 0,
          "content": "Lovely you on the way? I had other plans after the meet-up, I just gave ur IG to Charlie just in case, hope you don’t mind.",
          "time": "9:41am",
          "isRead": true
        },
        {
          "id": 1,
          "senderId": 1,
          "content": "Gosh I’m a bit under the weather, so I just came back to my flat. Would you pls let him know I’m gonna drop dm? So sorry, and thx for that. I don’t mind at all.",
          "time": "9:41am",
          "isRead": true
        },
        {
          "id": 2,
          "senderId": 0,
          "content": "Oooo sorry to hear that. Could you give just for a moment to see me? Cos I’m on the way to see you to bring your clothes that you’d left.",
          "time": "9:41am",
          "isRead": true
        },

        {
          "id": 3,
          "senderId": 1,
          "content": "Aww sweet, tysm! let me know when you arrive the ground floor!",
          "time": "9:41am",
          "isRead": true
        },
        {
          "id": 4,
          "senderId": 0,
          "content": "Hey lovey don’t forget to tell me when you are okay! Tmrw is the 24th and you leave soon!",
          "time": "9:41am",
          "isRead": true
        },
        {
          "id": 5,
          "senderId": 0,
          "content": "I couldn’t get to see Curtis or Senna so I should see you bfr you go!",
          "time": "9:41am",
          "isRead": true
        }
      ]
    }
  ]
}
